backupfinder/__init__.py
backupfinder/backup_finder.py
backupfinder/log_finder.py
backupfinder/main.py
backupfinder-0.1.3.dist-info/LICENSE
backupfinder-0.1.3.dist-info/METADATA
backupfinder-0.1.3.dist-info/WHEEL
backupfinder-0.1.3.dist-info/entry_points.txt
backupfinder-0.1.3.dist-info/top_level.txt
backupfinder-0.1.3.dist-info/RECORD
