Metadata-Version: 2.1
Name: backupfinder
Version: 0.1.3
Summary: A tool for generating log and backup wordlists based on domain URLs.
Home-page: https://github.com/pentestfunctions/custom-backup-finder/
Author: WOPRbot
Author-email: woprbot@hacknex.us
Classifier: Programming Language :: Python :: 3
Classifier: License :: OSI Approved :: MIT License
Classifier: Programming Language :: Python :: 3.8
Classifier: Programming Language :: Python :: 3.9
Classifier: Programming Language :: Python :: 3.10
Classifier: Programming Language :: Python :: 3.11
Requires-Python: >=3.6
License-File: LICENSE
